mls_2425_advanced_stats/__init__.py
mls_2425_advanced_stats/loader.py
mls_2425_advanced_stats/data/2023_DefensiveActions.csv
mls_2425_advanced_stats/data/2023_Goalkeeping.csv
mls_2425_advanced_stats/data/2023_Passing.csv
mls_2425_advanced_stats/data/2023_Possesion.csv
mls_2425_advanced_stats/data/2023_Preformance.csv
mls_2425_advanced_stats/data/2023_Shooting.csv
mls_2425_advanced_stats/data/2023_ShotGoalCreation.csv
mls_2425_advanced_stats/data/2023_standardStats.csv
mls_2425_advanced_stats/data/2024_DefensiveActions.csv
mls_2425_advanced_stats/data/2024_GoalShotCreation.csv
mls_2425_advanced_stats/data/2024_Goalkeeping.csv
mls_2425_advanced_stats/data/2024_Passing.csv
mls_2425_advanced_stats/data/2024_Possession.csv
mls_2425_advanced_stats/data/2024_Preformance.csv
mls_2425_advanced_stats/data/2024_Shooting.csv
mls_2425_advanced_stats/data/2024_roster_profiles_parsed.csv
mls_2425_advanced_stats/data/2024_standardStats.csv
mls_2425_advanced_stats/data/2025_BoxPreformance.csv
mls_2425_advanced_stats/data/2025_DefensiveActions.csv
mls_2425_advanced_stats/data/2025_GoalShotCreation.csv
mls_2425_advanced_stats/data/2025_Goalkeeping.csv
mls_2425_advanced_stats/data/2025_Passing.csv
mls_2425_advanced_stats/data/2025_Possesion.csv
mls_2425_advanced_stats/data/2025_Shooting.csv
mls_2425_advanced_stats/data/2025_Standard.csv
mls_2425_advanced_stats/data/2025_roster_profiles_parsed.csv
mls_2425_advanced_stats/data/fc25_fbref_position_mapping.csv
mls_2425_advanced_stats/data/fc25_manual_review.csv
mls_2425_advanced_stats/data/fc25_mls_positions.csv
mls_2425_advanced_stats/data/free_agents_2026.csv
mls_2425_advanced_stats/data/mls_salaries_all_classified.csv
mls_2425_advanced_stats/data/player_positions_granular.csv
mls_2425_advanced_stats-0.1.0.dist-info/METADATA
mls_2425_advanced_stats-0.1.0.dist-info/WHEEL
mls_2425_advanced_stats-0.1.0.dist-info/top_level.txt
mls_2425_advanced_stats-0.1.0.dist-info/RECORD
