Metadata-Version: 2.4
Name: mls-2425-advanced-stats
Version: 0.1.0
Summary: MLS 2023-2025 Advanced Player Statistics
Requires-Python: >=3.9
Requires-Dist: pandas
